LICENSE
README.rst
setup.cfg
setup.py
src/DICpy/__init__.py
src/DICpy/math4dic.py
src/DICpy/utils.py
src/DICpy.egg-info/PKG-INFO
src/DICpy.egg-info/SOURCES.txt
src/DICpy.egg-info/dependency_links.txt
src/DICpy.egg-info/requires.txt
src/DICpy.egg-info/top_level.txt
src/DICpy/DIC_2D/__init__.py
src/DICpy/DIC_2D/_coarse_fine.py
src/DICpy/DIC_2D/_gradient_one.py
src/DICpy/DIC_2D/_gradient_zero.py
src/DICpy/DIC_2D/_image_registration.py
src/DICpy/DIC_2D/_images.py
src/DICpy/DIC_2D/_lucas_kanade.py
src/DICpy/DIC_2D/_oversampling.py
src/DICpy/DIC_2D/_post_processing.py
src/DICpy/DIC_2D/_regular_grid.py
src/DICpy/DIC_2D/_synthetic.py