Metadata-Version: 1.1
Name: DICpy
Version: 0.3.1
Summary: Digital Image Correlation with Python.
Home-page: https://github.com/eesd-epfl/DICpy
Author: Ketson R. M. dos Santos
Author-email: ketson.santos@epfl.ch
License: MIT
Platform: OSX
Platform: Windows
Platform: Linux
Classifier: Programming Language :: Python :: 3
Classifier: Intended Audience :: Science/Research
Classifier: Topic :: Scientific/Engineering :: Image Processing
Classifier: License :: OSI Approved :: MIT License
Classifier: Natural Language :: English
